durandal/__init__.py
durandal/nlp.py
durandal-0.0.1.dist-info/LICENSE
durandal-0.0.1.dist-info/METADATA
durandal-0.0.1.dist-info/WHEEL
durandal-0.0.1.dist-info/top_level.txt
durandal-0.0.1.dist-info/RECORD
