Metadata-Version: 2.1
Name: durandal
Version: 0.0.1
Summary: Cutting Plane method to solve convex NLP with affine constratins
Home-page: https://github.com/DKenefake/durandal
Author: Dustin R. Kenefake
Author-email: Dustin.Kenefake@gmail.com
License: BSD 3.0
Platform: UNKNOWN
License-File: LICENSE
Requires-Dist: numpy
Requires-Dist: gurobipy
Provides-Extra: test
Requires-Dist: pytest ; extra == 'test'
